{
  "name": "Bernice Tate",
  "age": 19,
  "address": {
    "street": "Ihagu Heights",
    "city": "Pufabo",
    "state": "SC",
    "zip": "73133"
  },
  "contact": {
    "phone": "(253) 830-5833",
    "servicePhone": "800691144"
  },
  "birthday": "1984-10-21T23:58:22.538Z",
  "ip": "112.199.59.87",
  "foo": "bar",
  "profile": {
    "about": "Hi sibed mopalpuc viz vo to usulaf sanri fig imotewdug jewpuwo jetewekov cufhe oja. Ni fu cafuro fekeowe wowaf akananu kaj refiw uvtunic zec kor tet. Ecu powsur ofgunko su litarati ta kokhiup zujgi meluler tafi gulvu elases vovu unikowpa wat.",
    "bio": "Pase hudef hat gupurvu ozfelag zo hof ipwe wuhufmoz vedegmum tafjuh as na vudgu canzimpon cigumoh. Kavozgav ni dacocuh net regug bu vavajuse nivan ru wecabto omaimlis mujnihboh cucjoge ijood. Fik izera muh okwu le vibcuuz kimimeri urha ecaugutum le be pajzaze or mawmersev utpobi ojubuemo. Ija dunpaeba tugovfud udmifo deg zezut gugzodi fa pozef sijfuw cihe imioki dunife beljove koh vanpusi."
  },
  "apiKey": "6720d8f1ed3a019285f3673de244ddba3dc733c8b922789fcd88c3234e8dbb07",
  "currency": {
    "code": "XOF",
    "name": "Communauté Financière Africaine (BCEAO) Franc"
  }
}